{
  "$schema": "https://developer.microsoft.com/json-schemas/fabric/item/report/definition/visualContainer/2.7.0/schema.json",
  "name": "2e5e94dbbd18bbcc201c",
  "position": {
    "x": 519.60591133004925,
    "y": 109.95073891625616,
    "z": 18000,
    "height": 66.502463054187189,
    "width": 229.65517241379311,
    "tabOrder": 2000
  },
  "visual": {
    "visualType": "slicer",
    "query": {
      "queryState": {
        "Values": {
          "projections": [
            {
              "field": {
                "Column": {
                  "Expression": {
                    "SourceRef": {
                      "Entity": "SEKER"
                    }
                  },
                  "Property": "מגדר"
                }
              },
              "queryRef": "SEKER.מגדר",
              "nativeQueryRef": "מגדר",
              "active": true
            }
          ]
        }
      }
    },
    "objects": {
      "data": [
        {
          "properties": {
            "mode": {
              "expr": {
                "Literal": {
                  "Value": "'Basic'"
                }
              }
            }
          }
        }
      ],
      "general": [
        {
          "properties": {
            "orientation": {
              "expr": {
                "Literal": {
                  "Value": "1D"
                }
              }
            }
          }
        }
      ],
      "items": [
        {
          "properties": {
            "textSize": {
              "expr": {
                "Literal": {
                  "Value": "8D"
                }
              }
            }
          }
        }
      ],
      "header": [
        {
          "properties": {
            "textSize": {
              "expr": {
                "Literal": {
                  "Value": "8D"
                }
              }
            },
            "text": {
              "expr": {
                "Literal": {
                  "Value": "'מגדר'"
                }
              }
            }
          }
        }
      ],
      "selection": [
        {
          "properties": {
            "strictSingleSelect": {
              "expr": {
                "Literal": {
                  "Value": "false"
                }
              }
            }
          }
        }
      ]
    },
    "drillFilterOtherVisuals": true,
    "visualContainerObjects": {
      "general": [
        {
          "properties": {
            "altText": {
              "expr": {
                "Literal": {
                  "Value": "'סינון נתונים'"
                }
              }
            }
          }
        }
      ]
    }
  }
}