{
  "$schema": "https://developer.microsoft.com/json-schemas/fabric/item/report/definition/visualContainer/2.7.0/schema.json",
  "name": "1118f3eb55a4ce3c759d",
  "position": {
    "x": 63.191733639494835,
    "y": 105.07462686567165,
    "z": 4000,
    "height": 59.517795637198624,
    "width": 159.44890929965558,
    "tabOrder": 2000
  },
  "visual": {
    "visualType": "slicer",
    "query": {
      "queryState": {
        "Values": {
          "projections": [
            {
              "field": {
                "Column": {
                  "Expression": {
                    "SourceRef": {
                      "Entity": "DATA"
                    }
                  },
                  "Property": "שנה"
                }
              },
              "queryRef": "DATA.שנה",
              "nativeQueryRef": "שנה",
              "active": true
            }
          ]
        }
      },
      "sortDefinition": {
        "sort": [
          {
            "field": {
              "Column": {
                "Expression": {
                  "SourceRef": {
                    "Entity": "DATA"
                  }
                },
                "Property": "שנה"
              }
            },
            "direction": "Descending"
          }
        ]
      }
    },
    "objects": {
      "data": [
        {
          "properties": {
            "mode": {
              "expr": {
                "Literal": {
                  "Value": "'Dropdown'"
                }
              }
            }
          }
        }
      ],
      "selection": [
        {
          "properties": {
            "strictSingleSelect": {
              "expr": {
                "Literal": {
                  "Value": "true"
                }
              }
            }
          }
        }
      ],
      "general": [
        {
          "properties": {
            "filter": {
              "filter": {
                "Version": 2,
                "From": [
                  {
                    "Name": "d",
                    "Entity": "DATA",
                    "Type": 0
                  }
                ],
                "Where": [
                  {
                    "Condition": {
                      "In": {
                        "Expressions": [
                          {
                            "Column": {
                              "Expression": {
                                "SourceRef": {
                                  "Source": "d"
                                }
                              },
                              "Property": "שנה"
                            }
                          }
                        ],
                        "Values": [
                          [
                            {
                              "Literal": {
                                "Value": "'2023'"
                              }
                            }
                          ]
                        ]
                      }
                    }
                  }
                ]
              }
            }
          }
        }
      ],
      "header": [
        {
          "properties": {
            "textSize": {
              "expr": {
                "Literal": {
                  "Value": "8D"
                }
              }
            },
            "fontColor": {
              "solid": {
                "color": {
                  "expr": {
                    "Literal": {
                      "Value": "'#1F3A8A'"
                    }
                  }
                }
              }
            }
          }
        }
      ],
      "items": [
        {
          "properties": {
            "textSize": {
              "expr": {
                "Literal": {
                  "Value": "8D"
                }
              }
            }
          }
        }
      ]
    },
    "drillFilterOtherVisuals": true,
    "visualContainerObjects": {
      "general": [
        {
          "properties": {
            "altText": {
              "expr": {
                "Literal": {
                  "Value": "'סינון נתונים'"
                }
              }
            }
          }
        }
      ]
    }
  }
}